{
  "indexes": [
    {
      "collectionGroup": "messages",
      "queryScope": "COLLECTION",
      "fields": [
        { "fieldPath": "circleId", "order": "ASCENDING" },
        { "fieldPath": "createdAt", "order": "DESCENDING" }
      ]
    },
    {
      "collectionGroup": "journalEntries",
      "queryScope": "COLLECTION",
      "fields": [
        { "fieldPath": "authorId", "order": "ASCENDING" },
        { "fieldPath": "createdAt", "order": "DESCENDING" }
      ]
    }
  ],
  "fieldOverrides": []
} 